pyopds2/__init__.py
pyopds2/helpers.py
pyopds2/models.py
pyopds2/provider.py
pyopds2-0.1.0.dist-info/licenses/LICENSE
pyopds2-0.1.0.dist-info/METADATA
pyopds2-0.1.0.dist-info/WHEEL
pyopds2-0.1.0.dist-info/top_level.txt
pyopds2-0.1.0.dist-info/RECORD
